mqttutils/__init__.py
mqttutils-1.0.16.dist-info/METADATA
mqttutils-1.0.16.dist-info/WHEEL
mqttutils-1.0.16.dist-info/top_level.txt
mqttutils-1.0.16.dist-info/RECORD
