Metadata-Version: 2.1
Name: mqttutils
Version: 1.0.16
Summary: Mqtt utils python package
Classifier: Programming Language :: Python :: 3
Classifier: License :: OSI Approved :: MIT License
Classifier: Operating System :: OS Independent
Requires-Python: >=3.7.9
Requires-Dist: paho-mqtt <2.0,>=1.6
